Metadata-Version: 2.1
Name: pyeditorjs
Version: 1.0.0b0
Summary: pyEditorJS
Home-page: https://github.com/CWKevo/pyEditorJS
Author: SKevo
Author-email: skevo.cw@gmail.com
License: MIT
Keywords: editor.js,parser,clean,bleach,wysiwyg,editor,javascript,html,json
Classifier: Development Status :: 4 - Beta
Classifier: Intended Audience :: Developers
Classifier: License :: OSI Approved :: MIT License
Classifier: Programming Language :: Python :: 3.6
Classifier: Programming Language :: Python :: 3.7
Classifier: Programming Language :: Python :: 3.8
Classifier: Programming Language :: Python :: 3.9
Classifier: Programming Language :: Python :: 3.10
License-File: LICENSE
